mcp_audio_marge/__init__.py
mcp_audio_marge-0.1.8.dist-info/licenses/LICENSE
mcp_audio_marge-0.1.8.dist-info/METADATA
mcp_audio_marge-0.1.8.dist-info/WHEEL
mcp_audio_marge-0.1.8.dist-info/entry_points.txt
mcp_audio_marge-0.1.8.dist-info/top_level.txt
mcp_audio_marge-0.1.8.dist-info/RECORD
