Metadata-Version: 2.4
Name: mcp-audio-marge
Version: 0.1.8
Summary: A FastMCP server tool for audio synthesis using marge-server.
Author-email: Your Name <your.email@example.com>
Project-URL: Homepage, https://github.com/yourusername/mcp-audio-marge
Project-URL: Bug Tracker, https://github.com/yourusername/mcp-audio-marge/issues
Classifier: Programming Language :: Python :: 3
Classifier: License :: OSI Approved :: MIT License
Classifier: Operating System :: OS Independent
Requires-Python: >=3.7
License-File: LICENSE
Requires-Dist: fastmcp>=0.1.0
Requires-Dist: httpx>=0.23.0
Requires-Dist: pydantic>=1.0.0
Dynamic: license-file
